minivn/__init__.py
minivn/minivn.py
minivn-0.1.3.dist-info/METADATA
minivn-0.1.3.dist-info/WHEEL
minivn-0.1.3.dist-info/RECORD
